{"lastUsed":1590418866999,"path":"D:\/01_DHBW\/4_Semester\/2_Rechnertechnik\/Simulator_V1","projectCount":1,"recentFiles":[{"path":"\/Simulator_V1\/src","parentWorkspace":"D:\/01_DHBW\/4_Semester\/2_Rechnertechnik\/Simulator_V1","name":"Simulator_Window.java","lastModified":1590412719470},{"path":"\/Simulator_V1\/src","parentWorkspace":"D:\/01_DHBW\/4_Semester\/2_Rechnertechnik\/Simulator_V1","name":"Memory.java","lastModified":1590418867048,"locationURI":"file:\/D:\/01_DHBW\/4_Semester\/2_Rechnertechnik\/Simulator_V1\/Simulator_V1\/src\/Memory.java"},{"path":"\/Simulator_V1\/src","parentWorkspace":"D:\/01_DHBW\/4_Semester\/2_Rechnertechnik\/Simulator_V1","name":"Controller.java","lastModified":1590418251011,"locationURI":"file:\/D:\/01_DHBW\/4_Semester\/2_Rechnertechnik\/Simulator_V1\/Simulator_V1\/src\/Controller.java"},{"path":"\/Simulator_V1\/src","parentWorkspace":"D:\/01_DHBW\/4_Semester\/2_Rechnertechnik\/Simulator_V1","name":"Prozessor.java","lastModified":1590416602862,"locationURI":"file:\/D:\/01_DHBW\/4_Semester\/2_Rechnertechnik\/Simulator_V1\/Simulator_V1\/src\/Prozessor.java"}]}